[
  {
    "firstname": "facundo",
    "lastname": "castellano",
    "address": "deheza 64",
    "email": "facu@gmail.com",
    "age": "32",
    "sex": "male",
    "password": "$2b$10$hV8mVgb6046rPNc3OKn21O0nysTKlszl3mPHu6Dp1mAPLpnTFvF.a",
    "_id": "a065874e-1c10-4c7a-b2bf-fd8f044f4e26",
    "id": "a065874e-1c10-4c7a-b2bf-fd8f044f4e26",
    "createdAt": "2023-09-26T23:55:30.871Z",
    "updatedAt": "2023-09-26T23:55:30.871Z",
    "__v": 1
  },
  {
    "firstname": "martin",
    "lastname": "castellano",
    "address": "la casa de tinchex",
    "email": "martin@gmail.com",
    "age": "33",
    "sex": "male",
    "password": "$2b$10$HcflPAtcm1ecyqQYm0qgzebgld2YpuJrvmfXBiLBHiA6BuVcwyAw2",
    "_id": "0f53bfb8-47b8-42c8-9b7c-92776932d48b",
    "id": "0f53bfb8-47b8-42c8-9b7c-92776932d48b",
    "createdAt": "2023-09-27T13:02:33.251Z",
    "updatedAt": "2023-09-27T13:02:33.251Z",
    "__v": 1
  },
  {
    "firstname": "tomas",
    "lastname": "tosello",
    "address": "la casa de tom",
    "email": "tose@gmail.com",
    "age": "33",
    "sex": "male",
    "password": "$2b$10$x2e5YwQxrfUTl4k24JIkyuDiP0FLgfIrkSQ7M4aq7/b2S1/7O0LvW",
    "_id": "c736fbd1-e554-46ac-aaf3-eedbeb29b9a2",
    "id": "c736fbd1-e554-46ac-aaf3-eedbeb29b9a2",
    "createdAt": "2023-09-27T13:03:42.463Z",
    "updatedAt": "2023-09-27T13:03:42.463Z",
    "__v": 1
  },
  {
    "firstname": "male",
    "lastname": "castellano",
    "address": "la casa de male",
    "email": "male@gmail.com",
    "age": "36",
    "sex": "female",
    "password": "$2b$10$zl6sSqQbHKzkCDIK8CYB8ePjTN75OSnQuDXOw1Z4kkGJZoRXz6CGG",
    "_id": "8a473a96-f265-415d-b6c7-4b0d4fbb4da8",
    "id": "8a473a96-f265-415d-b6c7-4b0d4fbb4da8",
    "createdAt": "2023-09-27T13:06:42.675Z",
    "updatedAt": "2023-09-27T13:06:42.675Z",
    "__v": 1
  }
]
