[
  {
    "user": "a065874e-1c10-4c7a-b2bf-fd8f044f4e26",
    "products": [
      { "product": "001", "qty": 1 },
      { "product": "002", "qty": 12 },
      { "product": "003", "qty": 6 }
    ],
    "_id": "f82c2e33-c0ea-4ba3-856b-e681a703fcb1",
    "id": "f82c2e33-c0ea-4ba3-856b-e681a703fcb1",
    "createdAt": "2023-09-27T11:58:09.357Z",
    "updatedAt": "2023-09-27T11:58:09.357Z",
    "__v": 1
  },
  {
    "user": "8a473a96-f265-415d-b6c7-4b0d4fbb4da8",
    "products": [{ "product": "312", "qty": 64 }],
    "_id": "31955718-15eb-41c7-a0e1-a22a4ae20e23",
    "id": "31955718-15eb-41c7-a0e1-a22a4ae20e23",
    "createdAt": "2023-09-27T13:27:04.315Z",
    "updatedAt": "2023-09-27T13:27:04.315Z",
    "__v": 1
  }
]
